{"bugs":[{"priority":"--","assigned_to_detail":{"email":"kaie@kuix.de","real_name":"Kai Engert (:kaie:)","name":"kaie@kuix.de","id":36541},"blocks":[],"creator":"kaie@kuix.de","last_change_time":"2016-09-27T20:03:20Z","is_cc_accessible":true,"keywords":[],"creator_detail":{"email":"kaie@kuix.de","real_name":"Kai Engert (:kaie:)","name":"kaie@kuix.de","id":36541},"comment_count":51,"cf_qa_whiteboard":"","cc":["brian@briansmith.org","bugzilla@johnath.com","cww@mozilla.com","djcater+bugzilla@gmail.com","dolske@mozilla.com","dtownsend@mozilla.com","honzab.moz@firemni.cz","mak77@bonardo.net","matjk7@gmail.com","mcclown@gmail.com","mh+mozilla@glandium.org","n.nethercote@gmail.com","rrelyea@redhat.com","ted@mielczarek.org"],"url":"","assigned_to":"kaie@kuix.de","groups":[],"see_also":[],"id":673381,"whiteboard":"","creation_time":"2011-07-22T10:48:25Z","qa_contact":"","depends_on":[669061,673115,728719],"mentors":[],"dupe_of":null,"cf_status_firefox59":"---","cf_tracking_firefox59":"---","cf_fx_iteration":"---","cf_tracking_firefox_relnote":"---","cf_tracking_firefox58":"---","resolution":"FIXED","classification":"Graveyard","alias":null,"op_sys":"All","cf_last_resolved":"2012-03-13T12:42:37Z","cf_fx_points":"---","status":"RESOLVED","cf_tracking_firefox57":"---","cf_status_firefox58":"---","cc_detail":[{"email":"brian@briansmith.org","real_name":"Brian Smith (:briansmith, :bsmith, use NEEDINFO?)","name":"brian@briansmith.org","id":14661},{"email":"bugzilla@johnath.com","real_name":"Johnathan Nightingale [:johnath]","name":"bugzilla@johnath.com","id":210757},{"email":"cww@mozilla.com","real_name":"[:Cww]","name":"cww@mozilla.com","id":297228},{"email":"djcater+bugzilla@gmail.com","real_name":"Daniel Cater","name":"djcater+bugzilla@gmail.com","id":185959},{"email":"dolske@mozilla.com","real_name":"Justin Dolske [:Dolske]","name":"dolske@mozilla.com","id":27780},{"email":"dtownsend@mozilla.com","real_name":"Dave Townsend [:mossop]","name":"dtownsend@mozilla.com","id":91159},{"email":"honzab.moz@firemni.cz","real_name":"Honza Bambas (:mayhemer)","name":"honzab.moz@firemni.cz","id":269762},{"email":"mak77@bonardo.net","real_name":"Marco Bonardo [::mak]","name":"mak77@bonardo.net","id":240353},{"email":"matjk7@gmail.com","real_name":"Matheus Kerschbaum","name":"matjk7@gmail.com","id":383067},{"email":"mcclown@gmail.com","real_name":"Stephen Mc Gowan","name":"mcclown@gmail.com","id":401695},{"email":"mh+mozilla@glandium.org","real_name":"Mike Hommey [:glandium]","name":"mh+mozilla@glandium.org","id":47192},{"email":"n.nethercote@gmail.com","real_name":"Nicholas Nethercote [:njn]","name":"n.nethercote@gmail.com","id":334849},{"email":"rrelyea@redhat.com","real_name":"Robert Relyea","name":"rrelyea@redhat.com","id":11099},{"email":"ted@mielczarek.org","real_name":"Ted Mielczarek [:ted.mielczarek]","name":"ted@mielczarek.org","id":39022}],"summary":"about:support - add some runtime library version numbers (NSPR/NSS)","cf_user_story":"","is_open":false,"platform":"All","severity":"normal","votes":1,"flags":[],"cf_status_firefox_esr52":"---","version":"Trunk","cf_blocking_fx":"---","mentors_detail":[],"cf_tracking_firefox_esr52":"---","cf_status_firefox57":"---","component":"Security: UI","is_creator_accessible":true,"product":"Core Graveyard","is_confirmed":true,"target_milestone":"mozilla13"}],"faults":[]}