{"sha":"\"47e7bc67f932866e4467f7ab8a23bb167405bebd\"","commit":{"author":{"name":"\"Nicolas Silva\"","email":"\"nsilva@mozilla.com\"","date":"\"2016-09-01T15:51:09+02:00\""},"committer":{"name":"\"Nicolas Silva\"","email":"\"nsilva@mozilla.com\"","date":"\"2016-09-01T15:51:09+02:00\""},"message":"\"Bug 1298345 - Refactor CanvasRenderingContext2D's texture allocation code. r=Bas0dd298e\""},"diff":"\"0dd298e remove xxx comment, followup for 391288. r=cbarrett a=josh\\ndiff --git a/widget/src/cocoa/nsMenuX.mm b/widget/src/cocoa/nsMenuX.mm\\nindex 4bd25d6..3f45735 100644\\n--- a/widget/src/cocoa/nsMenuX.mm\\n+++ b/widget/src/cocoa/nsMenuX.mm\\n@@ -113,7 +113,7 @@ nsMenuX::~nsMenuX()\\n }\\n \\n \\n-NS_IMETHODIMP \\n+NS_IMETHODIMP\\n nsMenuX::Create(nsISupports * aParent, const nsAString &aLabel, const nsAString &aAccessKey, \\n                 nsIChangeManager* aManager, nsIContent* aNode)\\n {\\n@@ -142,16 +142,14 @@ nsMenuX::Create(nsISupports * aParent, const nsAString &aLabel, const nsAString\\n   if (menubar && mMenuContent->GetChildCount() == 0)\\n     mVisible = PR_FALSE;\\n \\n-  // XXXjag simply use mIsEnabled?\\n   SetEnabled(!mMenuContent->AttrValueIs(kNameSpaceID_None, nsWidgetAtoms::disabled,\\n                                         nsWidgetAtoms::_true, eCaseMatters));\\n+  [mNativeMenuItem setEnabled:(BOOL)mIsEnabled];\\n \\n   NSString *newCocoaLabelString = MenuHelpersX::CreateTruncatedCocoaLabel(mLabel);\\n   mNativeMenuItem = [[NSMenuItem alloc] initWithTitle:newCocoaLabelString action:nil keyEquivalent:@\\\"\\\"];\\n   [newCocoaLabelString release];\\n \\n-  [mNativeMenuItem setEnabled:(BOOL)mIsEnabled];\\n-\\n   // We call MenuConstruct here because keyboard commands are dependent upon\\n   // native menu items being created. If we only call MenuConstruct when a menu\\n   // is actually selected, then we can't access keyboard commands until the\\n\""}