{"sha":"\"47e7bc67f932866e4467f7ab8a23bb167405bebd\"","commit":{"author":{"name":"\"Nicolas Silva\"","email":"\"nsilva@mozilla.com\"","date":"\"2016-09-01T15:51:09+02:00\""},"committer":{"name":"\"Nicolas Silva\"","email":"\"nsilva@mozilla.com\"","date":"\"2016-09-01T15:51:09+02:00\""},"message":"\"Bug 1298345 - Refactor CanvasRenderingContext2D's texture allocation code. r=Bas178464c\""},"diff":"\"178464c Bug 396903 Fix .header-large dialog style to look like a wizard r=Mano a=dsicore\\ndiff --git a/toolkit/themes/pinstripe/global/dialog.css b/toolkit/themes/pinstripe/global/dialog.css\\nindex c4cc010..37bccf0 100644\\n--- a/toolkit/themes/pinstripe/global/dialog.css\\n+++ b/toolkit/themes/pinstripe/global/dialog.css\\n@@ -88,7 +88,7 @@ dialogheader {\\n \\n .header-large {\\n   -moz-box-orient: vertical;\\n-  margin: 0;\\n+  margin: -14px -14px 0;\\n   border-left: none;\\n   border-right: none;\\n   border-top: 1px solid;\\n@@ -128,4 +128,4 @@ dialogheader {\\n \\n #dialog.caseSensitive {\\n \\tmargin-top: 8px;\\n-}\\n\\\\ No newline at end of file\\n+}\\ndiff --git a/toolkit/themes/winstripe/global/dialog.css b/toolkit/themes/winstripe/global/dialog.css\\nindex 096347d..cc6ed9e 100644\\n--- a/toolkit/themes/winstripe/global/dialog.css\\n+++ b/toolkit/themes/winstripe/global/dialog.css\\n@@ -81,7 +81,10 @@ dialogheader {\\n \\n .header-large {\\n   -moz-box-orient: vertical;\\n-  margin: 0;\\n+  margin-top: -8px;\\n+  margin-bottom: 0;\\n+  -moz-margin-start: -8px;\\n+  -moz-margin-end: -10px;\\n   border-left: none;\\n   border-right: none;\\n   border-top: none;\\n@@ -90,8 +93,8 @@ dialogheader {\\n   padding-bottom: 12px;\\n   -moz-padding-start: 25px;\\n   -moz-padding-end: 5px;\\n-  background-color: -moz-Field;\\n-  color: -moz-FieldText;\\n+  background-color: Window;\\n+  color: WindowText;\\n }\\n \\n .header-large > .dialogheader-title {\\n\""}