{"sha":"\"47e7bc67f932866e4467f7ab8a23bb167405bebd\"","commit":{"author":{"name":"\"Nicolas Silva\"","email":"\"nsilva@mozilla.com\"","date":"\"2016-09-01T15:51:09+02:00\""},"committer":{"name":"\"Nicolas Silva\"","email":"\"nsilva@mozilla.com\"","date":"\"2016-09-01T15:51:09+02:00\""},"message":"\"Bug 1298345 - Refactor CanvasRenderingContext2D's texture allocation code. r=Bas37ed8d2\""},"diff":"\"37ed8d2 Fixing typo in comment.\\ndiff --git a/browser/base/content/tabbrowser.xml b/browser/base/content/tabbrowser.xml\\nindex f645afb..64d231b 100644\\n--- a/browser/base/content/tabbrowser.xml\\n+++ b/browser/base/content/tabbrowser.xml\\n@@ -1667,7 +1667,7 @@\\n                 secMan.checkLoadURIStr(sourceURI, aUrl,\\n                                        nsIScriptSecurityManager.STANDARD);\\n               } catch (e) {\\n-                // Stop even propagation right here.\\n+                // Stop event propagation right here.\\n                 aEvent.stopPropagation();\\n \\n                 throw \\\"Drop of \\\" + aUrl + \\\" denied.\\\";\\n\""}