{"sha":"\"47e7bc67f932866e4467f7ab8a23bb167405bebd\"","commit":{"author":{"name":"\"Nicolas Silva\"","email":"\"nsilva@mozilla.com\"","date":"\"2016-09-01T15:51:09+02:00\""},"committer":{"name":"\"Nicolas Silva\"","email":"\"nsilva@mozilla.com\"","date":"\"2016-09-01T15:51:09+02:00\""},"message":"\"Bug 1298345 - Refactor CanvasRenderingContext2D's texture allocation code. r=Bas55f121c\""},"diff":"\"55f121c Bug 347683 Fix some strict warnings r=mano\\ndiff --git a/browser/base/content/tabbrowser.xml b/browser/base/content/tabbrowser.xml\\nindex 45b7634..63a67db 100644\\n--- a/browser/base/content/tabbrowser.xml\\n+++ b/browser/base/content/tabbrowser.xml\\n@@ -1931,7 +1931,9 @@\\n \\n           aIndex = aIndex < aTab._tPos ? aIndex: aIndex+1;\\n           this.mCurrentTab.selected = false;\\n-          this.mTabContainer.insertBefore(aTab, this.mTabContainer.childNodes[aIndex]);\\n+          // use .item() instead of [] because dragging to the end of the strip goes out of\\n+          // bounds: .item() returns null (so it acts like appendChild), but [] throws\\n+          this.mTabContainer.insertBefore(aTab, this.mTabContainer.childNodes.item(aIndex));\\n           // invalidate cache, because mTabContainer is about to change\\n           this._browsers = null;\\n \\n\""}