{"sha":"\"47e7bc67f932866e4467f7ab8a23bb167405bebd\"","commit":{"author":{"name":"\"Nicolas Silva\"","email":"\"nsilva@mozilla.com\"","date":"\"2016-09-01T15:51:09+02:00\""},"committer":{"name":"\"Nicolas Silva\"","email":"\"nsilva@mozilla.com\"","date":"\"2016-09-01T15:51:09+02:00\""},"message":"\"Bug 1298345 - Refactor CanvasRenderingContext2D's texture allocation code. r=Bas64c8b13\""},"diff":"\"64c8b13 Bustage fix for Bug 390615. r+a=bsmedberg\\ndiff --git a/config/system-headers b/config/system-headers\\nindex 93fa0f8..c40e1dc 100644\\n--- a/config/system-headers\\n+++ b/config/system-headers\\n@@ -300,6 +300,7 @@ kernel/image.h\\n kernel/OS.h\\n key.h\\n keyt.h\\n+keythi.h\\n LAction.h\\n langinfo.h\\n LApplication.h\\n\""}