{"sha":"\"47e7bc67f932866e4467f7ab8a23bb167405bebd\"","commit":{"author":{"name":"\"Nicolas Silva\"","email":"\"nsilva@mozilla.com\"","date":"\"2016-09-01T15:51:09+02:00\""},"committer":{"name":"\"Nicolas Silva\"","email":"\"nsilva@mozilla.com\"","date":"\"2016-09-01T15:51:09+02:00\""},"message":"\"Bug 1298345 - Refactor CanvasRenderingContext2D's texture allocation code. r=Bas70adb9f\""},"diff":"\"70adb9f Bug 312896: tab strip should not respond to double click in space above and below tabs, r=mconnor\\ndiff --git a/browser/base/content/tabbrowser.xml b/browser/base/content/tabbrowser.xml\\nindex b0657a7..70f7861 100644\\n--- a/browser/base/content/tabbrowser.xml\\n+++ b/browser/base/content/tabbrowser.xml\\n@@ -1329,10 +1329,9 @@\\n         <parameter name=\\\"aEvent\\\"/>\\n         <body>\\n           <![CDATA[\\n-            if (aEvent.button == 0 && aEvent.originalTarget.localName != 'tab' &&\\n-                // Workaround to Bug 224002, the preventBubble() call in the tabbox binding\\n-                // should block this event.\\n-                aEvent.originalTarget.localName != \\\"toolbarbutton\\\") {\\n+            if (aEvent.button == 0 &&\\n+                // Only capture clicks on tabbox.xml's <spacer>\\n+                aEvent.originalTarget.localName == \\\"spacer\\\") {\\n               var e = document.createEvent(\\\"Events\\\");\\n               e.initEvent(\\\"NewTab\\\", false, true);\\n               this.dispatchEvent(e);\\n\""}