{"sha":"\"47e7bc67f932866e4467f7ab8a23bb167405bebd\"","commit":{"author":{"name":"\"Nicolas Silva\"","email":"\"nsilva@mozilla.com\"","date":"\"2016-09-01T15:51:09+02:00\""},"committer":{"name":"\"Nicolas Silva\"","email":"\"nsilva@mozilla.com\"","date":"\"2016-09-01T15:51:09+02:00\""},"message":"\"Bug 1298345 - Refactor CanvasRenderingContext2D's texture allocation code. r=Bas76ee3287\""},"diff":"\"76ee3287 Bug 390046: fix build break with Windows/mingw and OS/2 about undefined XRE_GetFileFromPath symbol, r=benjamin, a=bzbarsky\\ndiff --git a/toolkit/profile/src/Makefile.in b/toolkit/profile/src/Makefile.in\\nindex e8cf799..04f11ce 100644\\n--- a/toolkit/profile/src/Makefile.in\\n+++ b/toolkit/profile/src/Makefile.in\\n@@ -62,6 +62,8 @@ CPPSRCS = \\\\\\n \\t\\tnsToolkitProfileService.cpp \\\\\\n \\t\\t$(NULL)\\n \\n+DEFINES += -DIMPL_XREAPI\\n+\\n GARBAGE += nsProfileLock.cpp\\n \\n include $(topsrcdir)/config/rules.mk\\n\""}