{"sha":"\"47e7bc67f932866e4467f7ab8a23bb167405bebd\"","commit":{"author":{"name":"\"Nicolas Silva\"","email":"\"nsilva@mozilla.com\"","date":"\"2016-09-01T15:51:09+02:00\""},"committer":{"name":"\"Nicolas Silva\"","email":"\"nsilva@mozilla.com\"","date":"\"2016-09-01T15:51:09+02:00\""},"message":"\"Bug 1298345 - Refactor CanvasRenderingContext2D's texture allocation code. r=Basae217ec9\""},"diff":"\"ae217ec9 Bug 395986 - dropdown menu bgcolor on Applications tab is white-on-white. r+a=mconnor.\\ndiff --git a/toolkit/themes/pinstripe/global/menulist.css b/toolkit/themes/pinstripe/global/menulist.css\\nindex d82d161..55deba2 100644\\n--- a/toolkit/themes/pinstripe/global/menulist.css\\n+++ b/toolkit/themes/pinstripe/global/menulist.css\\n@@ -54,10 +54,9 @@ menulist {\\n \\n .menulist-label-box {\\n   -moz-appearance: menulist-text;\\n+  color: -moz-DialogText;\\n   -moz-box-align: center;\\n   -moz-box-pack: center;\\n-  background-color: #CCCCCC;\\n-border: 1px solid blue;\\n }\\n \\n .menulist-label {\\n\""}